<?xml version="1.0" encoding="UTF-8"?>
<MF0 version="1.1" packageUris="http://schema.mathworks.com/mf0/slsa_mm_param_graph/R2021b">
  <slsa.mm.param.graph.VariableRegistry type="slsa.mm.param.graph.VariableRegistry" uuid="4c0b2ec9-db70-433c-9873-99e94cb184cb">
    <name>model_try</name>
    <variables type="slsa.mm.param.graph.Variable" uuid="bf19263f-80e5-460c-915e-110e6021e296">
      <name>R</name>
      <workspace type="slsa.mm.param.graph.Workspace" uuid="cfdfb644-741d-4fbd-a441-6554141d009d"/>
    </variables>
    <workspaces type="slsa.mm.param.graph.Workspace" uuid="cfdfb644-741d-4fbd-a441-6554141d009d">
      <name>global-workspace</name>
      <variables type="slsa.mm.param.graph.Variable" uuid="bf19263f-80e5-460c-915e-110e6021e296"/>
    </workspaces>
    <contextManager type="slsa.mm.param.graph.ContextManager" uuid="38dcd8f5-dc2a-44d8-aa68-667b5c1f24e3"/>
  </slsa.mm.param.graph.VariableRegistry>
</MF0>